otterworks_drv8305.py
otterworks_circuitpython_drv8305-0.0.1.dist-info/LICENSE
otterworks_circuitpython_drv8305-0.0.1.dist-info/METADATA
otterworks_circuitpython_drv8305-0.0.1.dist-info/WHEEL
otterworks_circuitpython_drv8305-0.0.1.dist-info/top_level.txt
otterworks_circuitpython_drv8305-0.0.1.dist-info/RECORD
