Metadata-Version: 2.1
Name: otterworks-circuitpython-drv8305
Version: 0.0.1
Summary: CircuitPython library for the Texas Instruments DRV8305 Three-Phase Gate Driver
Home-page: UNKNOWN
Author: UNKNOWN
Author-email: UNKNOWN
License: MIT
Keywords: otterworks,drv8305,hardware,circuitpython,beaglebone
Platform: UNKNOWN
Classifier: Development Status :: 3 - Alpha
Classifier: Intended Audience :: Developers
Classifier: Topic :: Software Development :: Libraries
Classifier: Topic :: System :: Hardware
Classifier: License :: OSI Approved :: MIT License
Classifier: Programming Language :: Python :: 3
Classifier: Programming Language :: Python :: 3.5
Requires-Dist: Adafruit-Blinka
Requires-Dist: adafruit-circuitpython-busdevice
